bw2preagg/__init__.py
bw2preagg/balancing_presamples.py
bw2preagg/base_presamples.py
bw2preagg/concat_batches.py
bw2preagg/lci.py
bw2preagg/lcia.py
bw2preagg/setup_project.py
bw2preagg/utils.py
bw2preagg/verifs.py
bw2preagg/old/__init__.py
bw2preagg/old/build_A_B_samples.py
bw2preagg/old/check_AB.py
bw2preagg/old/concat_AB_samples.py
bw2preagg/old/create_presample_resource.py
bw2preagg/old/delete_bad_AB_sample_dirs.py
bw2preagg/old/generate_LCI_samples_using_presamples.py
tests/__init__.py
tests/conftest.py
tests/more_complicated_database.py
tests/test_preagg.py
bw2preagg-0.2.3.dist-info/LICENSE.txt
bw2preagg-0.2.3.dist-info/METADATA
bw2preagg-0.2.3.dist-info/WHEEL
bw2preagg-0.2.3.dist-info/top_level.txt
bw2preagg-0.2.3.dist-info/RECORD
